pyproject_starter/__init__.py
pyproject_starter/__main__.py
pyproject_starter/calculation.py
pyproject_starter/tests/__init__.py
pyproject_starter/tests/test_calculation.py
pyproject_starter-0.0.2.dist-info/METADATA
pyproject_starter-0.0.2.dist-info/WHEEL
pyproject_starter-0.0.2.dist-info/entry_points.txt
pyproject_starter-0.0.2.dist-info/licenses/LICENSE
pyproject_starter-0.0.2.dist-info/RECORD
