Metadata-Version: 2.4
Name: pyproject_starter
Version: 0.0.2
Summary: Python Package Cookiecutter Code
Project-URL: repository, https://github.com/vamseeachanta/pyproject_starter
Project-URL: documentation, https://github.com/vamseeachanta/pyproject_starter/blob/main/README.md
Project-URL: changelog, https://github.com/vamseeachanta/pyproject_starter/blob/main/CHANGELOG.md
Project-URL: issues, https://github.com/vamseeachanta/pyproject_starter/issues
Author-email: Vamsee Achanta <vamsee.achanta@aceengineer.com>
License: MIT License
License-File: LICENSE
Keywords: cookiecutter,library,module,package,template
Classifier: License :: OSI Approved :: MIT License
Classifier: Programming Language :: Python
Classifier: Programming Language :: Python :: 3
Classifier: Programming Language :: Python :: 3.8
Classifier: Programming Language :: Python :: 3.9
Classifier: Programming Language :: Python :: 3.10
Classifier: Programming Language :: Python :: 3.11
Classifier: Programming Language :: Python :: 3.12
Requires-Python: >=3.8
Requires-Dist: pyyaml>=6.0
Requires-Dist: tomli>=2.0.0; python_version < '3.11'
Provides-Extra: build
Requires-Dist: build>=0.10.0; extra == 'build'
Requires-Dist: twine>=4.0.0; extra == 'build'
Provides-Extra: dev
Requires-Dist: black>=23.0.0; extra == 'dev'
Requires-Dist: bumpver>=2023.1124; extra == 'dev'
Requires-Dist: isort>=5.12.0; extra == 'dev'
Requires-Dist: mypy>=1.0.0; extra == 'dev'
Requires-Dist: pre-commit>=3.0.0; extra == 'dev'
Requires-Dist: pytest>=7.0.0; extra == 'dev'
Provides-Extra: docs
Requires-Dist: sphinx-rtd-theme>=1.2.0; extra == 'docs'
Requires-Dist: sphinx>=5.0.0; extra == 'docs'
